IstioGuanfangWendangZhongwenban/README.md
IstioGuanfangWendangZhongwenban/__init__.py
IstioGuanfangWendangZhongwenban/__main__.py
IstioGuanfangWendangZhongwenban/file.epub
IstioGuanfangWendangZhongwenban/index.html
IstioGuanfangWendangZhongwenban/css/__init__.py
IstioGuanfangWendangZhongwenban/css/annotations.css
IstioGuanfangWendangZhongwenban/css/main.css
IstioGuanfangWendangZhongwenban/css/normalize.css
IstioGuanfangWendangZhongwenban/css/popup.css
IstioGuanfangWendangZhongwenban/font/__init__.py
IstioGuanfangWendangZhongwenban/font/fontello.eot
IstioGuanfangWendangZhongwenban/font/fontello.svg
IstioGuanfangWendangZhongwenban/font/fontello.ttf
IstioGuanfangWendangZhongwenban/font/fontello.woff
IstioGuanfangWendangZhongwenban/img/__init__.py
IstioGuanfangWendangZhongwenban/img/annotator-glyph-sprite.png
IstioGuanfangWendangZhongwenban/img/annotator-icon-sprite.png
IstioGuanfangWendangZhongwenban/img/apple-touch-icon.png
IstioGuanfangWendangZhongwenban/img/cancelfullscreen.png
IstioGuanfangWendangZhongwenban/img/close.png
IstioGuanfangWendangZhongwenban/img/fullscreen.png
IstioGuanfangWendangZhongwenban/img/loader.gif
IstioGuanfangWendangZhongwenban/img/menu-icon.png
IstioGuanfangWendangZhongwenban/img/save.png
IstioGuanfangWendangZhongwenban/img/saved.png
IstioGuanfangWendangZhongwenban/img/settings-s.png
IstioGuanfangWendangZhongwenban/img/settings.png
IstioGuanfangWendangZhongwenban/img/star.png
IstioGuanfangWendangZhongwenban/js/__init__.py
IstioGuanfangWendangZhongwenban/js/epub.js
IstioGuanfangWendangZhongwenban/js/epub.min.js
IstioGuanfangWendangZhongwenban/js/epub.min.map
IstioGuanfangWendangZhongwenban/js/hooks.min.js
IstioGuanfangWendangZhongwenban/js/hooks.min.map
IstioGuanfangWendangZhongwenban/js/reader.js
IstioGuanfangWendangZhongwenban/js/reader.js.map
IstioGuanfangWendangZhongwenban/js/reader.min.js
IstioGuanfangWendangZhongwenban/js/reader.min.map
IstioGuanfangWendangZhongwenban/js/hooks/__init__.py
istio_guanfang_wendang_zhongwenban-2024.3.4.0.dist-info/METADATA
istio_guanfang_wendang_zhongwenban-2024.3.4.0.dist-info/WHEEL
istio_guanfang_wendang_zhongwenban-2024.3.4.0.dist-info/entry_points.txt
istio_guanfang_wendang_zhongwenban-2024.3.4.0.dist-info/top_level.txt
istio_guanfang_wendang_zhongwenban-2024.3.4.0.dist-info/RECORD
